{"IlcelerResult":{"Ilce":[{"IlceAdi":"BAH\u00c7ESARAY","IlceAdiEn":"BAHCESARAY","IlceID":"9920"},{"IlceAdi":"BA\u015eKALE","IlceAdiEn":"BASKALE","IlceID":"9921"},{"IlceAdi":"\u00c7ALDIRAN","IlceAdiEn":"CALDIRAN","IlceID":"9922"},{"IlceAdi":"\u00c7ATAK","IlceAdiEn":"CATAK","IlceID":"9923"},{"IlceAdi":"EDREM\u0130T (V)","IlceAdiEn":"EDREMIT (V)","IlceID":"9924"},{"IlceAdi":"ERC\u0130\u015e","IlceAdiEn":"ERCIS","IlceID":"9925"},{"IlceAdi":"GEVA\u015e","IlceAdiEn":"GEVAS","IlceID":"9926"},{"IlceAdi":"G\u00dcRPINAR","IlceAdiEn":"G\u00dcRPINAR","IlceID":"17912"},{"IlceAdi":"MURAD\u0130YE","IlceAdiEn":"MURADIYE","IlceID":"9927"},{"IlceAdi":"\u00d6ZALP","IlceAdiEn":"OZALP","IlceID":"9928"},{"IlceAdi":"SARAY (V)","IlceAdiEn":"SARAY (V)","IlceID":"9929"},{"IlceAdi":"VAN","IlceAdiEn":"VAN","IlceID":"9930"}]}}